eazyAI/__init__.py
eazyAI/main.py
eazyAI-1.1.6.dist-info/LICENSE
eazyAI-1.1.6.dist-info/METADATA
eazyAI-1.1.6.dist-info/WHEEL
eazyAI-1.1.6.dist-info/top_level.txt
eazyAI-1.1.6.dist-info/RECORD
